dbt/__init__.py
dbt/redshift/__init__.py
dbt/redshift/redshift_etl.py
parsely_raw_data/__init__.py
parsely_raw_data/bigquery.py
parsely_raw_data/docgen.py
parsely_raw_data/redshift.py
parsely_raw_data/s3.py
parsely_raw_data/samples.py
parsely_raw_data/schema.py
parsely_raw_data/stream.py
parsely_raw_data/utils.py
parsely_raw_data/validate.py
tests/__init__.py
tests/test_basic.py
parsely_raw_data-2.4.3.dist-info/LICENSE
parsely_raw_data-2.4.3.dist-info/METADATA
parsely_raw_data-2.4.3.dist-info/WHEEL
parsely_raw_data-2.4.3.dist-info/entry_points.txt
parsely_raw_data-2.4.3.dist-info/top_level.txt
parsely_raw_data-2.4.3.dist-info/RECORD
