Metadata-Version: 2.1
Name: parsely-raw-data
Version: 2.4.3
Summary: Utilities for accessing the Parse.ly Data Pipeline
Home-page: https://github.com/Parsely/parsely_raw_data
Author: Emmett Butler
Author-email: support@parsely.com
License: Apache License 2.0
Keywords: parsely s3 kinesis redshift firehose bigquery
Platform: UNKNOWN
Classifier: Development Status :: 5 - Production/Stable
Classifier: Intended Audience :: Developers
Classifier: License :: OSI Approved :: Apache Software License
Classifier: Programming Language :: Python
Classifier: Programming Language :: Python :: 2
Classifier: Programming Language :: Python :: 2.7
Classifier: Programming Language :: Python :: 3
Classifier: Programming Language :: Python :: 3.4
Classifier: Programming Language :: Python :: 3.5
Classifier: Topic :: Software Development :: Libraries :: Python Modules
Requires-Dist: boto3
Requires-Dist: google-api-core (<1.24.0,>=1.16.0)
Requires-Dist: protobuf (<3.15,>=3.6.0)
Requires-Dist: google-api-python-client
Requires-Dist: psycopg2cffi-compat
Requires-Dist: six
Requires-Dist: tablib
Requires-Dist: xlsxwriter
Requires-Dist: tabulate
Requires-Dist: oauth2client
Requires-Dist: pytest
Requires-Dist: pyyaml
Provides-Extra: all
Requires-Dist: boto3 ; extra == 'all'
Requires-Dist: google-api-core (<1.24.0,>=1.16.0) ; extra == 'all'
Requires-Dist: protobuf (<3.15,>=3.6.0) ; extra == 'all'
Requires-Dist: google-api-python-client ; extra == 'all'
Requires-Dist: psycopg2cffi-compat ; extra == 'all'
Requires-Dist: six ; extra == 'all'
Requires-Dist: tablib ; extra == 'all'
Requires-Dist: xlsxwriter ; extra == 'all'
Requires-Dist: tabulate ; extra == 'all'
Requires-Dist: oauth2client ; extra == 'all'
Requires-Dist: pytest ; extra == 'all'
Requires-Dist: pyyaml ; extra == 'all'
Requires-Dist: thriftpy ; extra == 'all'
Requires-Dist: unittest2 ; extra == 'all'
Provides-Extra: dbt
Requires-Dist: dbt ; extra == 'dbt'
Requires-Dist: psycopg2 (==2.7.1) ; extra == 'dbt'
Provides-Extra: docs
Requires-Dist: pytest ; extra == 'docs'
Requires-Dist: thriftpy ; extra == 'docs'
Requires-Dist: unittest2 ; extra == 'docs'
Provides-Extra: lint
Requires-Dist: pep8 ; extra == 'lint'
Requires-Dist: pyflakes ; extra == 'lint'
Provides-Extra: test
Requires-Dist: pytest ; extra == 'test'
Requires-Dist: thriftpy ; extra == 'test'
Requires-Dist: unittest2 ; extra == 'test'
